<Properties>
  <MonoDevelop.Ide.Workbench ActiveDocument="ForceDropConfiguration.cs">
    <Files>
      <File FileName="ForceDrop.cs" Line="12" Column="5" />
      <File FileName="ForceDropConfiguration.cs" Line="1" Column="1" />
    </Files>
  </MonoDevelop.Ide.Workbench>
  <MonoDevelop.Ide.DebuggingService.PinnedWatches />
  <MonoDevelop.Ide.Workspace ActiveConfiguration="Debug" />
  <MonoDevelop.Ide.DebuggingService.Breakpoints>
    <BreakpointStore />
  </MonoDevelop.Ide.DebuggingService.Breakpoints>
  <MultiItemStartupConfigurations />
</Properties>